bakedbeans
