Metadata-Version: 1.1
Name: bakedbeans
Version: 0.1.3
Summary: Canned response HTTP server
Home-page: https://github.com/a-musing-moose/bakedbeans
Author: Jonathan Moss
Author-email: jmoss@commoncode.io
License: MIT
Platform: UNKNOWN
Classifier: Intended Audience :: Developers
Classifier: Topic :: Utilities
Classifier: Programming Language :: Python :: 3.6
